ot_class/__init__.py
ot_class/graph_utils.py
ot_class/helpers.py
ot_class/pd_alg.py
ot_class/ppoisson.py
ot_class/wass_dist.py
ot_class-0.2.dist-info/LICENSE
ot_class-0.2.dist-info/METADATA
ot_class-0.2.dist-info/WHEEL
ot_class-0.2.dist-info/top_level.txt
ot_class-0.2.dist-info/RECORD
